pyrsa/__init__.py
pyrsa/data/__init__.py
pyrsa/data/computations.py
pyrsa/data/dataset.py
pyrsa/data/neurodataset.py
pyrsa/data/noise.py
pyrsa/inference/__init__.py
pyrsa/inference/boot_testset.py
pyrsa/inference/bootstrap.py
pyrsa/inference/crossvalsets.py
pyrsa/inference/evaluate.py
pyrsa/inference/noise_ceiling.py
pyrsa/inference/result.py
pyrsa/io/__init__.py
pyrsa/io/meadows.py
pyrsa/model/__init__.py
pyrsa/model/fitter.py
pyrsa/model/model.py
pyrsa/rdm/__init__.py
pyrsa/rdm/calc.py
pyrsa/rdm/compare.py
pyrsa/rdm/rdms.py
pyrsa/simulation/__init__.py
pyrsa/simulation/sim.py
pyrsa/util/__init__.py
pyrsa/util/data_utils.py
pyrsa/util/descriptor_utils.py
pyrsa/util/file_io.py
pyrsa/util/inference_util.py
pyrsa/util/matrix.py
pyrsa/util/rdm_utils.py
pyrsa/util/searchlight.py
pyrsa/util/vis_utils.py
pyrsa/vis/__init__.py
pyrsa/vis/colors.py
pyrsa/vis/icon.py
pyrsa/vis/mds_plot.py
pyrsa/vis/model_plot.py
pyrsa/vis/rdm_plot.py
tests/__init__.py
tests/test_colors.py
tests/test_crossval.py
tests/test_data.py
tests/test_data_utils.py
tests/test_descriptor_utils.py
tests/test_inference.py
tests/test_io_meadows.py
tests/test_model.py
tests/test_noise_ceiling.py
tests/test_rdm.py
tests/test_searchlight.py
tests/test_simulation.py
tests/test_something.py
tests/test_util_matrix.py
tests/test_util_rdm.py
tests/test_vis.py
rsa3-3.0.0.post20201106.dist-info/AUTHORS
rsa3-3.0.0.post20201106.dist-info/LICENSE
rsa3-3.0.0.post20201106.dist-info/METADATA
rsa3-3.0.0.post20201106.dist-info/WHEEL
rsa3-3.0.0.post20201106.dist-info/top_level.txt
rsa3-3.0.0.post20201106.dist-info/RECORD
