Metadata-Version: 2.1
Name: rsa3
Version: 3.0.0.post20201106
Summary: Python Representational Similarity Analysis (RSA)
Home-page: https://github.com/rsagroup/pyrsa
Author: pyrsa authors
Author-email: 
License: UNKNOWN
Keywords: neuroscience
Platform: UNKNOWN
Classifier: Programming Language :: Python
Classifier: License :: OSI Approved :: MIT License
Classifier: Operating System :: OS Independent
Classifier: Development Status :: 4 - Beta
Classifier: Topic :: Scientific/Engineering
Classifier: Intended Audience :: Science/Research
Classifier: Programming Language :: Python :: 3.6
Classifier: Programming Language :: Python :: 3.7
Requires-Dist: coverage
Requires-Dist: h5py
Requires-Dist: joblib
Requires-Dist: matplotlib
Requires-Dist: numpy
Requires-Dist: scikit-image
Requires-Dist: scikit-learn
Requires-Dist: scipy
Requires-Dist: tqdm
